{
"meta":{"test_sets":[],"test_metrics":[],"learn_metrics":[{"best_value":"Min","name":"RMSE"}],"launch_mode":"Train","parameters":"","iteration_count":500,"learn_sets":["learn"],"name":"experiment"},
"iterations":[
{"learn":[11631801.6],"iteration":0,"passed_time":0.1392262249,"remaining_time":69.47388625},
{"learn":[11581388.93],"iteration":1,"passed_time":0.1398550025,"remaining_time":34.82389562},
{"learn":[11540185.85],"iteration":2,"passed_time":0.1403957076,"remaining_time":23.25888889},
{"learn":[11496079.38],"iteration":3,"passed_time":0.1408589796,"remaining_time":17.46651347},
{"learn":[11464588.75],"iteration":4,"passed_time":0.1415420389,"remaining_time":14.01266185},
{"learn":[11425927.69],"iteration":5,"passed_time":0.1420432203,"remaining_time":11.69489181},
{"learn":[11385411.71],"iteration":6,"passed_time":0.1424581593,"remaining_time":10.03312465},
{"learn":[11358220.21],"iteration":7,"passed_time":0.1430637239,"remaining_time":8.798419019},
{"learn":[11315034.66],"iteration":8,"passed_time":0.1436703614,"remaining_time":7.838016382},
{"learn":[11275858.35],"iteration":9,"passed_time":0.1441120183,"remaining_time":7.061488896},
{"learn":[11228602.09],"iteration":10,"passed_time":0.1446352139,"remaining_time":6.42969269},
{"learn":[11194701.02],"iteration":11,"passed_time":0.1449079427,"remaining_time":5.892923005},
{"learn":[11156031.58],"iteration":12,"passed_time":0.1454069854,"remaining_time":5.447169375},
{"learn":[11108386.97],"iteration":13,"passed_time":0.1459098422,"remaining_time":5.065155951},
{"learn":[11064310.33],"iteration":14,"passed_time":0.1464094161,"remaining_time":4.733904453},
{"learn":[11021520.91],"iteration":15,"passed_time":0.1470494684,"remaining_time":4.44824642},
{"learn":[10978595.86],"iteration":16,"passed_time":0.147517624,"remaining_time":4.191236024},
{"learn":[10936266.52],"iteration":17,"passed_time":0.1479618785,"remaining_time":3.962090302},
{"learn":[10895015.23],"iteration":18,"passed_time":0.1484149381,"remaining_time":3.757241327},
{"learn":[10857942.78],"iteration":19,"passed_time":0.1488562137,"remaining_time":3.57254913},
{"learn":[10812408.6],"iteration":20,"passed_time":0.1499562326,"remaining_time":3.420430258},
{"learn":[10768466.83],"iteration":21,"passed_time":0.1504972175,"remaining_time":3.269894088},
{"learn":[10728009.22],"iteration":22,"passed_time":0.1509184271,"remaining_time":3.129916945},
{"learn":[10688370.59],"iteration":23,"passed_time":0.1513209665,"remaining_time":3.001199168},
{"learn":[10648379.71],"iteration":24,"passed_time":0.1517324802,"remaining_time":2.882917125},
{"learn":[10636445.97],"iteration":25,"passed_time":0.1519537709,"remaining_time":2.770234132},
{"learn":[10594497.5],"iteration":26,"passed_time":0.1523485161,"remaining_time":2.6689203},
{"learn":[10549196.99],"iteration":27,"passed_time":0.1528128539,"remaining_time":2.575988109},
{"learn":[10509720.08],"iteration":28,"passed_time":0.153330343,"remaining_time":2.49029626},
{"learn":[10475938.14],"iteration":29,"passed_time":0.1537916389,"remaining_time":2.409402342},
{"learn":[10434537.17],"iteration":30,"passed_time":0.1542246251,"remaining_time":2.333269328},
{"learn":[10393303.63],"iteration":31,"passed_time":0.1548238985,"remaining_time":2.264299515},
{"learn":[10356839.72],"iteration":32,"passed_time":0.1553100719,"remaining_time":2.197872836},
{"learn":[10316808.12],"iteration":33,"passed_time":0.1558012715,"remaining_time":2.135393897},
{"learn":[10279858.78],"iteration":34,"passed_time":0.1563494724,"remaining_time":2.07721442},
{"learn":[10240026.75],"iteration":35,"passed_time":0.1567909155,"remaining_time":2.020860688},
{"learn":[10208093.65],"iteration":36,"passed_time":0.1572639763,"remaining_time":1.967924893},
{"learn":[10178722.8],"iteration":37,"passed_time":0.1576850403,"remaining_time":1.917118122},
{"learn":[10139422.56],"iteration":38,"passed_time":0.1581002699,"remaining_time":1.868826267},
{"learn":[10100285.57],"iteration":39,"passed_time":0.1585424204,"remaining_time":1.823237835},
{"learn":[10060474.21],"iteration":40,"passed_time":0.1590318249,"remaining_time":1.780380674},
{"learn":[10030407.04],"iteration":41,"passed_time":0.1599608726,"remaining_time":1.74433523},
{"learn":[10007936.36],"iteration":42,"passed_time":0.1606701919,"remaining_time":1.707587854},
{"learn":[9973065.899],"iteration":43,"passed_time":0.1611406979,"remaining_time":1.670003596},
{"learn":[9935060.318],"iteration":44,"passed_time":0.1615934254,"remaining_time":1.633889079},
{"learn":[9906090.101],"iteration":45,"passed_time":0.162115602,"remaining_time":1.600010506},
{"learn":[9870643.563],"iteration":46,"passed_time":0.1624733303,"remaining_time":1.565966354},
{"learn":[9836208.464],"iteration":47,"passed_time":0.1630612614,"remaining_time":1.535493545},
{"learn":[9800020.569],"iteration":48,"passed_time":0.1638252593,"remaining_time":1.50786106},
{"learn":[9764621.534],"iteration":49,"passed_time":0.1642532534,"remaining_time":1.478279281},
{"learn":[9727954.095],"iteration":50,"passed_time":0.1646615977,"remaining_time":1.449667792},
{"learn":[9708044.764],"iteration":51,"passed_time":0.1650511129,"remaining_time":1.421978819},
{"learn":[9674554.121],"iteration":52,"passed_time":0.1654424739,"remaining_time":1.395335581},
{"learn":[9643554.048],"iteration":53,"passed_time":0.1658286405,"remaining_time":1.369621735},
{"learn":[9608117.645],"iteration":54,"passed_time":0.166374574,"remaining_time":1.346121554},
{"learn":[9573525.774],"iteration":55,"passed_time":0.1670858671,"remaining_time":1.324752232},
{"learn":[9540069.21],"iteration":56,"passed_time":0.1678765274,"remaining_time":1.304724591},
{"learn":[9508259.459],"iteration":57,"passed_time":0.1683381674,"remaining_time":1.282852931},
{"learn":[9479002.117],"iteration":58,"passed_time":0.1687570058,"remaining_time":1.261387111},
{"learn":[9446609.981],"iteration":59,"passed_time":0.1691720145,"remaining_time":1.240594773},
{"learn":[9413812.161],"iteration":60,"passed_time":0.1695586229,"remaining_time":1.220266155},
{"learn":[9383021.253],"iteration":61,"passed_time":0.1701877104,"remaining_time":1.202293825},
{"learn":[9349770.36],"iteration":62,"passed_time":0.1707621055,"remaining_time":1.1844927},
{"learn":[9317779.31],"iteration":63,"passed_time":0.1712310127,"remaining_time":1.166511274},
{"learn":[9283124.301],"iteration":64,"passed_time":0.1717056227,"remaining_time":1.149106859},
{"learn":[9258900.049],"iteration":65,"passed_time":0.1721525576,"remaining_time":1.132033485},
{"learn":[9228391.317],"iteration":66,"passed_time":0.1726089064,"remaining_time":1.115517261},
{"learn":[9196360.577],"iteration":67,"passed_time":0.1730760274,"remaining_time":1.099541821},
{"learn":[9166181.739],"iteration":68,"passed_time":0.1736756948,"remaining_time":1.084843833},
{"learn":[9141244.949],"iteration":69,"passed_time":0.1741248786,"remaining_time":1.069624254},
{"learn":[9121840.23],"iteration":70,"passed_time":0.1745230001,"remaining_time":1.054512212},
{"learn":[9089094.948],"iteration":71,"passed_time":0.1749138985,"remaining_time":1.039765952},
{"learn":[9064987.604],"iteration":72,"passed_time":0.1752311516,"remaining_time":1.024982215},
{"learn":[9033098.326],"iteration":73,"passed_time":0.1756249862,"remaining_time":1.011030326},
{"learn":[9002049.073],"iteration":74,"passed_time":0.176013397,"remaining_time":0.9974092497},
{"learn":[8976061.861],"iteration":75,"passed_time":0.1762347404,"remaining_time":0.9832043412},
{"learn":[8953492.909],"iteration":76,"passed_time":0.1767129007,"remaining_time":0.9707734674},
{"learn":[8921812.974],"iteration":77,"passed_time":0.1772054719,"remaining_time":0.9587270403},
{"learn":[8897038.825],"iteration":78,"passed_time":0.177593744,"remaining_time":0.9464172942},
{"learn":[8869291.344],"iteration":79,"passed_time":0.1779682868,"remaining_time":0.9343335056},
{"learn":[8839751.755],"iteration":80,"passed_time":0.1783842928,"remaining_time":0.9227533172},
{"learn":[8809229.457],"iteration":81,"passed_time":0.1787657402,"remaining_time":0.9112692609},
{"learn":[8780913.367],"iteration":82,"passed_time":0.1791507561,"remaining_time":0.900070666},
{"learn":[8755642.731],"iteration":83,"passed_time":0.1795471587,"remaining_time":0.889185929},
{"learn":[8726935.68],"iteration":84,"passed_time":0.1800576571,"remaining_time":0.8791050319},
{"learn":[8702297.959],"iteration":85,"passed_time":0.1805924371,"remaining_time":0.8693635927},
{"learn":[8677557.247],"iteration":86,"passed_time":0.181054446,"remaining_time":0.859488347},
{"learn":[8648989.766],"iteration":87,"passed_time":0.181469736,"remaining_time":0.8496083093},
{"learn":[8627133.997],"iteration":88,"passed_time":0.1819096307,"remaining_time":0.8400545867},
{"learn":[8602490.916],"iteration":89,"passed_time":0.1823424674,"remaining_time":0.8306712403},
{"learn":[8580241.045],"iteration":90,"passed_time":0.1827693689,"remaining_time":0.8214579328},
{"learn":[8555710.64],"iteration":91,"passed_time":0.1831921586,"remaining_time":0.8124173992},
{"learn":[8531003.656],"iteration":92,"passed_time":0.1837374959,"remaining_time":0.8040985034},
{"learn":[8508248.673],"iteration":93,"passed_time":0.1841424894,"remaining_time":0.7953388372},
{"learn":[8484871.855],"iteration":94,"passed_time":0.1845481711,"remaining_time":0.7867579924},
{"learn":[8460355.156],"iteration":95,"passed_time":0.1849415647,"remaining_time":0.7782957514},
{"learn":[8435612.307],"iteration":96,"passed_time":0.1853427735,"remaining_time":0.7700323476},
{"learn":[8414449.071],"iteration":97,"passed_time":0.1857574575,"remaining_time":0.7619846726},
{"learn":[8390131.569],"iteration":98,"passed_time":0.186156877,"remaining_time":0.7540293703},
{"learn":[8375468.365],"iteration":99,"passed_time":0.1865398432,"remaining_time":0.7461593727},
{"learn":[8348537.611],"iteration":100,"passed_time":0.187028577,"remaining_time":0.7388554674},
{"learn":[8326699.324],"iteration":101,"passed_time":0.1876073666,"remaining_time":0.7320365875},
{"learn":[8299641.492],"iteration":102,"passed_time":0.1880290358,"remaining_time":0.7247332741},
{"learn":[8275495.311],"iteration":103,"passed_time":0.1884518147,"remaining_time":0.7175665254},
{"learn":[8250039.689],"iteration":104,"passed_time":0.1888423621,"remaining_time":0.7104069811},
{"learn":[8229520.276],"iteration":105,"passed_time":0.1892573746,"remaining_time":0.7034660906},
{"learn":[8209704.514],"iteration":106,"passed_time":0.1896493742,"remaining_time":0.6965626547},
{"learn":[8195421.059],"iteration":107,"passed_time":0.1900489471,"remaining_time":0.6898072895},
{"learn":[8181491.075],"iteration":108,"passed_time":0.190634949,"remaining_time":0.6838372942},
{"learn":[8160138.209],"iteration":109,"passed_time":0.1910654819,"remaining_time":0.6774139811},
{"learn":[8135594.684],"iteration":110,"passed_time":0.191461969,"remaining_time":0.6709793328},
{"learn":[8110245.021],"iteration":111,"passed_time":0.1918592365,"remaining_time":0.6646552122},
{"learn":[8091885.616],"iteration":112,"passed_time":0.1922525728,"remaining_time":0.6584225281},
{"learn":[8067825.551],"iteration":113,"passed_time":0.1926732199,"remaining_time":0.652384762},
{"learn":[8044876.49],"iteration":114,"passed_time":0.1931174472,"remaining_time":0.6465236277},
{"learn":[8028513.282],"iteration":115,"passed_time":0.1935094964,"remaining_time":0.6405831604},
{"learn":[8006349.548],"iteration":116,"passed_time":0.1945310364,"remaining_time":0.6367981789},
{"learn":[7986408.775],"iteration":117,"passed_time":0.1949489704,"remaining_time":0.631105989},
{"learn":[7967944.533],"iteration":118,"passed_time":0.19534463,"remaining_time":0.6254311262},
{"learn":[7950590.986],"iteration":119,"passed_time":0.1957280425,"remaining_time":0.619805468},
{"learn":[7933415.259],"iteration":120,"passed_time":0.1961108917,"remaining_time":0.6142646939},
{"learn":[7909876.714],"iteration":121,"passed_time":0.1965181395,"remaining_time":0.6088840716},
{"learn":[7889582.202],"iteration":122,"passed_time":0.1969108923,"remaining_time":0.6035398894},
{"learn":[7868286.212],"iteration":123,"passed_time":0.1975562766,"remaining_time":0.5990416128},
{"learn":[7845026.133],"iteration":124,"passed_time":0.1979934536,"remaining_time":0.5939803609},
{"learn":[7833577.954],"iteration":125,"passed_time":0.1984094775,"remaining_time":0.5889297189},
{"learn":[7812358.223],"iteration":126,"passed_time":0.1989700912,"remaining_time":0.5843767246},
{"learn":[7792444.989],"iteration":127,"passed_time":0.1993183996,"remaining_time":0.5792690987},
{"learn":[7770896.09],"iteration":128,"passed_time":0.199735382,"remaining_time":0.5744327653},
{"learn":[7751445.818],"iteration":129,"passed_time":0.2001984788,"remaining_time":0.5697956706},
{"learn":[7733207.376],"iteration":130,"passed_time":0.200729583,"remaining_time":0.5654138635},
{"learn":[7711013.78],"iteration":131,"passed_time":0.20117084,"remaining_time":0.5608399176},
{"learn":[7689544.896],"iteration":132,"passed_time":0.2015949929,"remaining_time":0.5562809202},
{"learn":[7670213.65],"iteration":133,"passed_time":0.2020130036,"remaining_time":0.5517668607},
{"learn":[7652765.852],"iteration":134,"passed_time":0.2024249886,"remaining_time":0.5472971913},
{"learn":[7635245.393],"iteration":135,"passed_time":0.2028576028,"remaining_time":0.5429424076},
{"learn":[7617796.409],"iteration":136,"passed_time":0.2032925745,"remaining_time":0.5386511279},
{"learn":[7597711.789],"iteration":137,"passed_time":0.2037610357,"remaining_time":0.5345035865},
{"learn":[7573583.89],"iteration":138,"passed_time":0.2042464172,"remaining_time":0.5304529252},
{"learn":[7560594.32],"iteration":139,"passed_time":0.2046073506,"remaining_time":0.5261331874},
{"learn":[7540101.072],"iteration":140,"passed_time":0.2054763136,"remaining_time":0.5231630963},
{"learn":[7519828.774],"iteration":141,"passed_time":0.2058859001,"remaining_time":0.5190644524},
{"learn":[7499734.145],"iteration":142,"passed_time":0.2062840386,"remaining_time":0.5149888237},
{"learn":[7482418.452],"iteration":143,"passed_time":0.2066808094,"remaining_time":0.5109608899},
{"learn":[7464869.208],"iteration":144,"passed_time":0.207069476,"remaining_time":0.5069631998},
{"learn":[7457402.716],"iteration":145,"passed_time":0.2074508024,"remaining_time":0.5029971511},
{"learn":[7438400.729],"iteration":146,"passed_time":0.2079462858,"remaining_time":0.4993540061},
{"learn":[7415932.433],"iteration":147,"passed_time":0.2084361192,"remaining_time":0.4957399593},
{"learn":[7400905.836],"iteration":148,"passed_time":0.2088897209,"remaining_time":0.4920824969},
{"learn":[7381281.076],"iteration":149,"passed_time":0.2092814097,"remaining_time":0.4883232893},
{"learn":[7366792.08],"iteration":150,"passed_time":0.2096606539,"remaining_time":0.484579922},
{"learn":[7352442.509],"iteration":151,"passed_time":0.2100539933,"remaining_time":0.48091309},
{"learn":[7335459.387],"iteration":152,"passed_time":0.2104411364,"remaining_time":0.4772749956},
{"learn":[7318493.539],"iteration":153,"passed_time":0.2108269195,"remaining_time":0.4736760658},
{"learn":[7302989.475],"iteration":154,"passed_time":0.2111997109,"remaining_time":0.470089679},
{"learn":[7289160.084],"iteration":155,"passed_time":0.2117693076,"remaining_time":0.4669784731},
{"learn":[7277302.127],"iteration":156,"passed_time":0.212394696,"remaining_time":0.4640215333},
{"learn":[7259477.862],"iteration":157,"passed_time":0.2129527347,"remaining_time":0.4609483244},
{"learn":[7242281.743],"iteration":158,"passed_time":0.2133410138,"remaining_time":0.4575426774},
{"learn":[7228561.074],"iteration":159,"passed_time":0.2137315758,"remaining_time":0.4541795986},
{"learn":[7215871.276],"iteration":160,"passed_time":0.2141067765,"remaining_time":0.4508211008},
{"learn":[7200012.387],"iteration":161,"passed_time":0.2145085091,"remaining_time":0.4475547907},
{"learn":[7184584.129],"iteration":162,"passed_time":0.2150312568,"remaining_time":0.4445738254},
{"learn":[7169378.418],"iteration":163,"passed_time":0.2156669479,"remaining_time":0.4418542347},
{"learn":[7154393.815],"iteration":164,"passed_time":0.2160834677,"remaining_time":0.4387149193},
{"learn":[7136536.187],"iteration":165,"passed_time":0.2164589016,"remaining_time":0.4355257418},
{"learn":[7124197.051],"iteration":166,"passed_time":0.2168507438,"remaining_time":0.4324029802},
{"learn":[7110255.124],"iteration":167,"passed_time":0.2171390867,"remaining_time":0.4291081952},
{"learn":[7097716.72],"iteration":168,"passed_time":0.2175439834,"remaining_time":0.4260772692},
{"learn":[7083495.308],"iteration":169,"passed_time":0.2179538117,"remaining_time":0.4230868109},
{"learn":[7069795.93],"iteration":170,"passed_time":0.2183582744,"remaining_time":0.4201162122},
{"learn":[7058316.407],"iteration":171,"passed_time":0.2188204847,"remaining_time":0.4172855755},
{"learn":[7043245.066],"iteration":172,"passed_time":0.2192253279,"remaining_time":0.4143738857},
{"learn":[7031065.518],"iteration":173,"passed_time":0.2196401111,"remaining_time":0.4115096335},
{"learn":[7019859.01],"iteration":174,"passed_time":0.2200856186,"remaining_time":0.4087304346},
{"learn":[7006874.555],"iteration":175,"passed_time":0.2205303946,"remaining_time":0.4059764083},
{"learn":[6991384.692],"iteration":176,"passed_time":0.2209593427,"remaining_time":0.4032195916},
{"learn":[6976159.014],"iteration":177,"passed_time":0.2213912658,"remaining_time":0.4004943123},
{"learn":[6961022.544],"iteration":178,"passed_time":0.2219047872,"remaining_time":0.3979409871},
{"learn":[6946783.681],"iteration":179,"passed_time":0.2223504582,"remaining_time":0.3952897035},
{"learn":[6933078.75],"iteration":180,"passed_time":0.2227755604,"remaining_time":0.3926265401},
{"learn":[6922109.698],"iteration":181,"passed_time":0.223233352,"remaining_time":0.3900450876},
{"learn":[6910168.478],"iteration":182,"passed_time":0.2237122977,"remaining_time":0.3875234884},
{"learn":[6897110.248],"iteration":183,"passed_time":0.2241819845,"remaining_time":0.3850081908},
{"learn":[6883598.626],"iteration":184,"passed_time":0.2246545983,"remaining_time":0.3825199916},
{"learn":[6871244.562],"iteration":185,"passed_time":0.2252529014,"remaining_time":0.3802656508},
{"learn":[6857065.216],"iteration":186,"passed_time":0.22572827,"remaining_time":0.3778232541},
{"learn":[6843637.23],"iteration":187,"passed_time":0.2262414132,"remaining_time":0.375464473},
{"learn":[6831305.594],"iteration":188,"passed_time":0.226659276,"remaining_time":0.3729684383},
{"learn":[6820321.911],"iteration":189,"passed_time":0.2271174102,"remaining_time":0.3705599851},
{"learn":[6807902.756],"iteration":190,"passed_time":0.2275537736,"remaining_time":0.3681367332},
{"learn":[6793386.538],"iteration":191,"passed_time":0.2279813284,"remaining_time":0.3657200476},
{"learn":[6782053.878],"iteration":192,"passed_time":0.2283745252,"remaining_time":0.3632693224},
{"learn":[6769149.13],"iteration":193,"passed_time":0.2288461648,"remaining_time":0.3609635383},
{"learn":[6758924.108],"iteration":194,"passed_time":0.229277113,"remaining_time":0.3586129203},
{"learn":[6746730.642],"iteration":195,"passed_time":0.22967756,"remaining_time":0.3562345829},
{"learn":[6733386.037],"iteration":196,"passed_time":0.2300796949,"remaining_time":0.3538789215},
{"learn":[6724180.173],"iteration":197,"passed_time":0.2304859151,"remaining_time":0.351549224},
{"learn":[6719135.075],"iteration":198,"passed_time":0.2307693759,"remaining_time":0.3490531767},
{"learn":[6708914.574],"iteration":199,"passed_time":0.2311511356,"remaining_time":0.3467267034},
{"learn":[6698061.221],"iteration":200,"passed_time":0.2315440844,"remaining_time":0.3444362251},
{"learn":[6684369.285],"iteration":201,"passed_time":0.2321229194,"remaining_time":0.3424387623},
{"learn":[6672441.97],"iteration":202,"passed_time":0.2326227006,"remaining_time":0.3403396161},
{"learn":[6666434.032],"iteration":203,"passed_time":0.2329719907,"remaining_time":0.3380377905},
{"learn":[6659495.025],"iteration":204,"passed_time":0.2334617606,"remaining_time":0.3359571677},
{"learn":[6651323.921],"iteration":205,"passed_time":0.2339120843,"remaining_time":0.3338356931},
{"learn":[6642605.979],"iteration":206,"passed_time":0.2343475302,"remaining_time":0.331709306},
{"learn":[6633639.873],"iteration":207,"passed_time":0.2347840191,"remaining_time":0.3296006422},
{"learn":[6620294.969],"iteration":208,"passed_time":0.2351919194,"remaining_time":0.3274681748},
{"learn":[6607032.861],"iteration":209,"passed_time":0.2357128754,"remaining_time":0.3255082565},
{"learn":[6601998.598],"iteration":210,"passed_time":0.2361153318,"remaining_time":0.3233996725},
{"learn":[6591415.155],"iteration":211,"passed_time":0.2365785294,"remaining_time":0.3213897004},
{"learn":[6582455.035],"iteration":212,"passed_time":0.2370467315,"remaining_time":0.319400995},
{"learn":[6572535.951],"iteration":213,"passed_time":0.2375081529,"remaining_time":0.317417438},
{"learn":[6559958.519],"iteration":214,"passed_time":0.2379644234,"remaining_time":0.3154412125},
{"learn":[6548093.525],"iteration":215,"passed_time":0.2384251188,"remaining_time":0.3134848784},
{"learn":[6540746.073],"iteration":216,"passed_time":0.2389713398,"remaining_time":0.3116538671},
{"learn":[6529098.348],"iteration":217,"passed_time":0.239649557,"remaining_time":0.3100053902},
{"learn":[6519411.637],"iteration":218,"passed_time":0.2400986958,"remaining_time":0.3080718426},
{"learn":[6509861.98],"iteration":219,"passed_time":0.2405279152,"remaining_time":0.3061264375},
{"learn":[6501262.689],"iteration":220,"passed_time":0.2409283072,"remaining_time":0.3041583606},
{"learn":[6488405.748],"iteration":221,"passed_time":0.241328407,"remaining_time":0.3022040412},
{"learn":[6474144.134],"iteration":222,"passed_time":0.2417459807,"remaining_time":0.3002853662},
{"learn":[6469747.882],"iteration":223,"passed_time":0.2421191898,"remaining_time":0.2983254303},
{"learn":[6463088.34],"iteration":224,"passed_time":0.2425516143,"remaining_time":0.296451973},
{"learn":[6455846.185],"iteration":225,"passed_time":0.2430113533,"remaining_time":0.2946243841},
{"learn":[6444193.667],"iteration":226,"passed_time":0.2434138586,"remaining_time":0.2927400149},
{"learn":[6431562.004],"iteration":227,"passed_time":0.2438306512,"remaining_time":0.2908856891},
{"learn":[6420525.569],"iteration":228,"passed_time":0.2442555774,"remaining_time":0.2890535435},
{"learn":[6412106.786],"iteration":229,"passed_time":0.2446784741,"remaining_time":0.2872312522},
{"learn":[6398275.403],"iteration":230,"passed_time":0.2451095362,"remaining_time":0.2854305854},
{"learn":[6389101.114],"iteration":231,"passed_time":0.2456114166,"remaining_time":0.283723533},
{"learn":[6380674.937],"iteration":232,"passed_time":0.2461472985,"remaining_time":0.2820657884},
{"learn":[6369601.609],"iteration":233,"passed_time":0.2466957413,"remaining_time":0.280431911},
{"learn":[6361265.893],"iteration":234,"passed_time":0.2473608339,"remaining_time":0.2789388127},
{"learn":[6353090.398],"iteration":235,"passed_time":0.2478630049,"remaining_time":0.2772704801},
{"learn":[6344548.403],"iteration":236,"passed_time":0.2482497287,"remaining_time":0.2754838762},
{"learn":[6339612.908],"iteration":237,"passed_time":0.2485453172,"remaining_time":0.2736087105},
{"learn":[6328784.162],"iteration":238,"passed_time":0.2489476985,"remaining_time":0.2718633862},
{"learn":[6318547.657],"iteration":239,"passed_time":0.2494825141,"remaining_time":0.2702727236},
{"learn":[6306711.307],"iteration":240,"passed_time":0.2501216633,"remaining_time":0.2688029493},
{"learn":[6302845.01],"iteration":241,"passed_time":0.2503651332,"remaining_time":0.2669181998},
{"learn":[6292902.434],"iteration":242,"passed_time":0.2508028542,"remaining_time":0.2652524014},
{"learn":[6283591.719],"iteration":243,"passed_time":0.2512240182,"remaining_time":0.2635792978},
{"learn":[6275755.324],"iteration":244,"passed_time":0.2516600305,"remaining_time":0.2619318685},
{"learn":[6270700.544],"iteration":245,"passed_time":0.2520989244,"remaining_time":0.2602972635},
{"learn":[6262964.555],"iteration":246,"passed_time":0.2525212492,"remaining_time":0.2586553687},
{"learn":[6255008.891],"iteration":247,"passed_time":0.2530099435,"remaining_time":0.257090749},
{"learn":[6245353.782],"iteration":248,"passed_time":0.2534320358,"remaining_time":0.2554676345},
{"learn":[6239316.316],"iteration":249,"passed_time":0.2538555052,"remaining_time":0.2538555052},
{"learn":[6233953.974],"iteration":250,"passed_time":0.2542355429,"remaining_time":0.2522097617},
{"learn":[6226592.628],"iteration":251,"passed_time":0.2546330181,"remaining_time":0.2505912242},
{"learn":[6222333.091],"iteration":252,"passed_time":0.2549534507,"remaining_time":0.2489071239},
{"learn":[6216111.073],"iteration":253,"passed_time":0.2553519558,"remaining_time":0.2473093745},
{"learn":[6205133.777],"iteration":254,"passed_time":0.2557997149,"remaining_time":0.2457683535},
{"learn":[6197466.796],"iteration":255,"passed_time":0.2563637112,"remaining_time":0.2443466622},
{"learn":[6191861.605],"iteration":256,"passed_time":0.2568608537,"remaining_time":0.2428684337},
{"learn":[6184482.642],"iteration":257,"passed_time":0.2573006322,"remaining_time":0.2413440039},
{"learn":[6175083.465],"iteration":258,"passed_time":0.2577161423,"remaining_time":0.2398053679},
{"learn":[6168471.755],"iteration":259,"passed_time":0.2581149806,"remaining_time":0.2382599821},
{"learn":[6159442.533],"iteration":260,"passed_time":0.2585246516,"remaining_time":0.2367333016},
{"learn":[6150083.872],"iteration":261,"passed_time":0.2589054728,"remaining_time":0.2351889409},
{"learn":[6137604.704],"iteration":262,"passed_time":0.2594357834,"remaining_time":0.2337881394},
{"learn":[6131756.747],"iteration":263,"passed_time":0.2598756579,"remaining_time":0.2323130882},
{"learn":[6123295.35],"iteration":264,"passed_time":0.2602980788,"remaining_time":0.2308303718},
{"learn":[6113239.475],"iteration":265,"passed_time":0.2606931006,"remaining_time":0.2293315246},
{"learn":[6107832.87],"iteration":266,"passed_time":0.261098449,"remaining_time":0.2278499574},
{"learn":[6103706.407],"iteration":267,"passed_time":0.2614955476,"remaining_time":0.22636928},
{"learn":[6096730.511],"iteration":268,"passed_time":0.2618924369,"remaining_time":0.2248964793},
{"learn":[6089402.179],"iteration":269,"passed_time":0.262275538,"remaining_time":0.2234199027},
{"learn":[6081141.214],"iteration":270,"passed_time":0.2626598076,"remaining_time":0.2219523836},
{"learn":[6076456.556],"iteration":271,"passed_time":0.2634067241,"remaining_time":0.2207968128},
{"learn":[6070606.846],"iteration":272,"passed_time":0.2640072575,"remaining_time":0.2195225181},
{"learn":[6063851.778],"iteration":273,"passed_time":0.2644743746,"remaining_time":0.2181430973},
{"learn":[6055124.662],"iteration":274,"passed_time":0.2648815496,"remaining_time":0.2167212679},
{"learn":[6048662.783],"iteration":275,"passed_time":0.2651729744,"remaining_time":0.2152128488},
{"learn":[6039926.048],"iteration":276,"passed_time":0.2655535964,"remaining_time":0.2137850253},
{"learn":[6032132.626],"iteration":277,"passed_time":0.2660463095,"remaining_time":0.2124542471},
{"learn":[6024569.701],"iteration":278,"passed_time":0.266831946,"remaining_time":0.2113615056},
{"learn":[6020128.685],"iteration":279,"passed_time":0.2671775142,"remaining_time":0.2099251897},
{"learn":[6010809.644],"iteration":280,"passed_time":0.2675706187,"remaining_time":0.2085336851},
{"learn":[6003234.231],"iteration":281,"passed_time":0.2679814785,"remaining_time":0.2071629869},
{"learn":[5996376.487],"iteration":282,"passed_time":0.2682701484,"remaining_time":0.2057053788},
{"learn":[5988167.93],"iteration":283,"passed_time":0.2686737633,"remaining_time":0.2043434256},
{"learn":[5981229.132],"iteration":284,"passed_time":0.2690629127,"remaining_time":0.202977285},
{"learn":[5971353.365],"iteration":285,"passed_time":0.2695029136,"remaining_time":0.2016560262},
{"learn":[5968197.556],"iteration":286,"passed_time":0.2699839422,"remaining_time":0.2003713578},
{"learn":[5961728.456],"iteration":287,"passed_time":0.270423138,"remaining_time":0.1990614766},
{"learn":[5958732.203],"iteration":288,"passed_time":0.2706436933,"remaining_time":0.1975979906},
{"learn":[5949932.873],"iteration":289,"passed_time":0.2710436978,"remaining_time":0.1962730226},
{"learn":[5944982.201],"iteration":290,"passed_time":0.2714450771,"remaining_time":0.194955399},
{"learn":[5938073.906],"iteration":291,"passed_time":0.271837554,"remaining_time":0.1936377097},
{"learn":[5934137.998],"iteration":292,"passed_time":0.2722210828,"remaining_time":0.1923200141},
{"learn":[5929130.289],"iteration":293,"passed_time":0.2726745434,"remaining_time":0.1910576733},
{"learn":[5921934.098],"iteration":294,"passed_time":0.2731419202,"remaining_time":0.1898104869},
{"learn":[5917029.831],"iteration":295,"passed_time":0.2735357873,"remaining_time":0.1885179075},
{"learn":[5911562.35],"iteration":296,"passed_time":0.273915016,"remaining_time":0.1872213746},
{"learn":[5908657.161],"iteration":297,"passed_time":0.2742968671,"remaining_time":0.1859327757},
{"learn":[5900313.841],"iteration":298,"passed_time":0.2747145113,"remaining_time":0.1846743036},
{"learn":[5893497.756],"iteration":299,"passed_time":0.2750975163,"remaining_time":0.1833983442},
{"learn":[5883313.979],"iteration":300,"passed_time":0.2754966312,"remaining_time":0.1821389688},
{"learn":[5876361.001],"iteration":301,"passed_time":0.2759817081,"remaining_time":0.1809416497},
{"learn":[5872758.656],"iteration":302,"passed_time":0.276798119,"remaining_time":0.1799644536},
{"learn":[5868408.151],"iteration":303,"passed_time":0.2772550892,"remaining_time":0.1787565707},
{"learn":[5861219.74],"iteration":304,"passed_time":0.2776732131,"remaining_time":0.1775287756},
{"learn":[5856344.129],"iteration":305,"passed_time":0.2780633629,"remaining_time":0.1762885373},
{"learn":[5850642.116],"iteration":306,"passed_time":0.278445011,"remaining_time":0.1750484922},
{"learn":[5846234.072],"iteration":307,"passed_time":0.2788425551,"remaining_time":0.1738239305},
{"learn":[5840586.355],"iteration":308,"passed_time":0.2792178418,"remaining_time":0.1725909637},
{"learn":[5835811.862],"iteration":309,"passed_time":0.2798533159,"remaining_time":0.1715230001},
{"learn":[5830129.047],"iteration":310,"passed_time":0.2802708578,"remaining_time":0.1703253766},
{"learn":[5823971.115],"iteration":311,"passed_time":0.2806311225,"remaining_time":0.1690982405},
{"learn":[5816215.663],"iteration":312,"passed_time":0.2810772136,"remaining_time":0.1679279199},
{"learn":[5813227.153],"iteration":313,"passed_time":0.2815231899,"remaining_time":0.1667621444},
{"learn":[5809873.647],"iteration":314,"passed_time":0.2821188587,"remaining_time":0.1656888535},
{"learn":[5803853.873],"iteration":315,"passed_time":0.282547913,"remaining_time":0.1645215696},
{"learn":[5799723.355],"iteration":316,"passed_time":0.2830418295,"remaining_time":0.1633963874},
{"learn":[5790582.66],"iteration":317,"passed_time":0.2837422821,"remaining_time":0.1623933816},
{"learn":[5781295.676],"iteration":318,"passed_time":0.2841688922,"remaining_time":0.1612368949},
{"learn":[5778519.947],"iteration":319,"passed_time":0.2846064296,"remaining_time":0.1600911166},
{"learn":[5774551.994],"iteration":320,"passed_time":0.2848644519,"remaining_time":0.1588496476},
{"learn":[5768139.751],"iteration":321,"passed_time":0.2852994405,"remaining_time":0.1577121131},
{"learn":[5763400.027],"iteration":322,"passed_time":0.2856761508,"remaining_time":0.1565469928},
{"learn":[5759938.354],"iteration":323,"passed_time":0.2861878096,"remaining_time":0.1554600447},
{"learn":[5756180.048],"iteration":324,"passed_time":0.2869034465,"remaining_time":0.1544864712},
{"learn":[5753296.992],"iteration":325,"passed_time":0.2874125872,"remaining_time":0.1534042643},
{"learn":[5749281.664],"iteration":326,"passed_time":0.2878919242,"remaining_time":0.1523097948},
{"learn":[5743426.326],"iteration":327,"passed_time":0.2883536045,"remaining_time":0.151209817},
{"learn":[5736670.614],"iteration":328,"passed_time":0.2887840436,"remaining_time":0.1500974816},
{"learn":[5733410.816],"iteration":329,"passed_time":0.2892097889,"remaining_time":0.1489868609},
{"learn":[5730878.468],"iteration":330,"passed_time":0.2901481133,"remaining_time":0.1481420881},
{"learn":[5727390.984],"iteration":331,"passed_time":0.2906302811,"remaining_time":0.1470659254},
{"learn":[5722614.309],"iteration":332,"passed_time":0.2911103388,"remaining_time":0.145992272},
{"learn":[5719203.182],"iteration":333,"passed_time":0.2915045538,"remaining_time":0.1448795088},
{"learn":[5713950.092],"iteration":334,"passed_time":0.2919251041,"remaining_time":0.1437840065},
{"learn":[5708307.557],"iteration":335,"passed_time":0.2923366395,"remaining_time":0.1426881217},
{"learn":[5700624.016],"iteration":336,"passed_time":0.2927752959,"remaining_time":0.1416094161},
{"learn":[5696609.982],"iteration":337,"passed_time":0.2943020284,"remaining_time":0.1410560018},
{"learn":[5692622.034],"iteration":338,"passed_time":0.2947161281,"remaining_time":0.1399684266},
{"learn":[5689064.002],"iteration":339,"passed_time":0.2951742278,"remaining_time":0.138905519},
{"learn":[5684147.992],"iteration":340,"passed_time":0.2955872365,"remaining_time":0.1378251337},
{"learn":[5678187.59],"iteration":341,"passed_time":0.2959890063,"remaining_time":0.136743459},
{"learn":[5672269.271],"iteration":342,"passed_time":0.2965446648,"remaining_time":0.1357361877},
{"learn":[5667162.04],"iteration":343,"passed_time":0.2970088605,"remaining_time":0.1346900646},
{"learn":[5659322.401],"iteration":344,"passed_time":0.2975262255,"remaining_time":0.1336712028},
{"learn":[5651904.765],"iteration":345,"passed_time":0.298029932,"remaining_time":0.1326491605},
{"learn":[5649345.648],"iteration":346,"passed_time":0.2984399781,"remaining_time":0.1315888088},
{"learn":[5645125.089],"iteration":347,"passed_time":0.2988291453,"remaining_time":0.1305230749},
{"learn":[5637581.1],"iteration":348,"passed_time":0.2992444562,"remaining_time":0.1294725298},
{"learn":[5633272.902],"iteration":349,"passed_time":0.2996560436,"remaining_time":0.1284240187},
{"learn":[5628784.422],"iteration":350,"passed_time":0.3001666249,"remaining_time":0.1274211599},
{"learn":[5626803.693],"iteration":351,"passed_time":0.3005528756,"remaining_time":0.1263688227},
{"learn":[5623887.047],"iteration":352,"passed_time":0.3009975563,"remaining_time":0.1253445914},
{"learn":[5620050.658],"iteration":353,"passed_time":0.3013944317,"remaining_time":0.1243039182},
{"learn":[5614867.988],"iteration":354,"passed_time":0.3017830588,"remaining_time":0.1232635029},
{"learn":[5611291.374],"iteration":355,"passed_time":0.3021680088,"remaining_time":0.122225262},
{"learn":[5607010.783],"iteration":356,"passed_time":0.3025648772,"remaining_time":0.121195455},
{"learn":[5601902.444],"iteration":357,"passed_time":0.30295952,"remaining_time":0.1201683012},
{"learn":[5597839.441],"iteration":358,"passed_time":0.30334415,"remaining_time":0.1191407386},
{"learn":[5593437.041],"iteration":359,"passed_time":0.3039275854,"remaining_time":0.118194061},
{"learn":[5585008.382],"iteration":360,"passed_time":0.3047269195,"remaining_time":0.1173325258},
{"learn":[5581109.311],"iteration":361,"passed_time":0.3053642178,"remaining_time":0.1164095637},
{"learn":[5575381.575],"iteration":362,"passed_time":0.3057853035,"remaining_time":0.1154065746},
{"learn":[5567217.67],"iteration":363,"passed_time":0.3061902164,"remaining_time":0.1144007402},
{"learn":[5563454.799],"iteration":364,"passed_time":0.3065024054,"remaining_time":0.1133639034},
{"learn":[5560103.15],"iteration":365,"passed_time":0.3070173561,"remaining_time":0.1124052615},
{"learn":[5557059.736],"iteration":366,"passed_time":0.307612341,"remaining_time":0.1114780418},
{"learn":[5553870.231],"iteration":367,"passed_time":0.3086258993,"remaining_time":0.1107027682},
{"learn":[5550355.627],"iteration":368,"passed_time":0.3090929056,"remaining_time":0.1097321698},
{"learn":[5547004.431],"iteration":369,"passed_time":0.3094925127,"remaining_time":0.1087406126},
{"learn":[5544246.139],"iteration":370,"passed_time":0.3098979944,"remaining_time":0.1077542892},
{"learn":[5541764.349],"iteration":371,"passed_time":0.3104401304,"remaining_time":0.1068181094},
{"learn":[5537722.895],"iteration":372,"passed_time":0.3108933019,"remaining_time":0.1058537516},
{"learn":[5532944.892],"iteration":373,"passed_time":0.3113463259,"remaining_time":0.1048920777},
{"learn":[5526639.509],"iteration":374,"passed_time":0.3117485731,"remaining_time":0.103916191},
{"learn":[5524863.831],"iteration":375,"passed_time":0.3119816535,"remaining_time":0.1028875666},
{"learn":[5521306.582],"iteration":376,"passed_time":0.3123904458,"remaining_time":0.1019204903},
{"learn":[5516225.934],"iteration":377,"passed_time":0.312769139,"remaining_time":0.1009466533},
{"learn":[5514484.632],"iteration":378,"passed_time":0.3129875408,"remaining_time":0.09992478215},
{"learn":[5509838.394],"iteration":379,"passed_time":0.3133672879,"remaining_time":0.09895809093},
{"learn":[5502735.851],"iteration":380,"passed_time":0.3138492523,"remaining_time":0.0980264069},
{"learn":[5499341.351],"iteration":381,"passed_time":0.3142579128,"remaining_time":0.09707443381},
{"learn":[5493668.236],"iteration":382,"passed_time":0.3146831688,"remaining_time":0.09613036749},
{"learn":[5488240.3],"iteration":383,"passed_time":0.3150783006,"remaining_time":0.0951799033},
{"learn":[5480990.296],"iteration":384,"passed_time":0.3154813095,"remaining_time":0.09423467687},
{"learn":[5479324.872],"iteration":385,"passed_time":0.3157119211,"remaining_time":0.09324134456},
{"learn":[5476665.56],"iteration":386,"passed_time":0.3160125155,"remaining_time":0.09227238826},
{"learn":[5471890.376],"iteration":387,"passed_time":0.3164012108,"remaining_time":0.09133230827},
{"learn":[5469144.908],"iteration":388,"passed_time":0.3167786487,"remaining_time":0.09039185091},
{"learn":[5465987.27],"iteration":389,"passed_time":0.3172900607,"remaining_time":0.08949206841},
{"learn":[5464332.315],"iteration":390,"passed_time":0.3177231903,"remaining_time":0.08857244948},
{"learn":[5459654.109],"iteration":391,"passed_time":0.3181524344,"remaining_time":0.08765424214},
{"learn":[5457048.216],"iteration":392,"passed_time":0.3185650455,"remaining_time":0.08673399458},
{"learn":[5451600.504],"iteration":393,"passed_time":0.3189701034,"remaining_time":0.08581429177},
{"learn":[5447112.807],"iteration":394,"passed_time":0.3193705233,"remaining_time":0.08489596188},
{"learn":[5442244.775],"iteration":395,"passed_time":0.3197590566,"remaining_time":0.08397712597},
{"learn":[5440458.469],"iteration":396,"passed_time":0.3200722382,"remaining_time":0.08304141193},
{"learn":[5437033.777],"iteration":397,"passed_time":0.3204887487,"remaining_time":0.08213530746},
{"learn":[5433477.503],"iteration":398,"passed_time":0.3209354403,"remaining_time":0.08123929693},
{"learn":[5430186.039],"iteration":399,"passed_time":0.3215826406,"remaining_time":0.08039566016},
{"learn":[5425145.995],"iteration":400,"passed_time":0.322059623,"remaining_time":0.07951097925},
{"learn":[5422440.518],"iteration":401,"passed_time":0.3225280211,"remaining_time":0.07862623401},
{"learn":[5416987.241],"iteration":402,"passed_time":0.3229974058,"remaining_time":0.07774379245},
{"learn":[5413051.861],"iteration":403,"passed_time":0.3234638518,"remaining_time":0.07686269747},
{"learn":[5409820.471],"iteration":404,"passed_time":0.3240826894,"remaining_time":0.07601939628},
{"learn":[5406281.772],"iteration":405,"passed_time":0.3245554062,"remaining_time":0.07514336991},
{"learn":[5403317.171],"iteration":406,"passed_time":0.3249954854,"remaining_time":0.07426186766},
{"learn":[5397434.602],"iteration":407,"passed_time":0.3254625568,"remaining_time":0.07338861575},
{"learn":[5394502.466],"iteration":408,"passed_time":0.3259290912,"remaining_time":0.07251723057},
{"learn":[5392154.402],"iteration":409,"passed_time":0.3263819691,"remaining_time":0.07164482248},
{"learn":[5387942.239],"iteration":410,"passed_time":0.3268396089,"remaining_time":0.07077548708},
{"learn":[5380678.187],"iteration":411,"passed_time":0.327401218,"remaining_time":0.06993035725},
{"learn":[5376590.714],"iteration":412,"passed_time":0.3279195188,"remaining_time":0.06907747733},
{"learn":[5370758.573],"iteration":413,"passed_time":0.3283933089,"remaining_time":0.06821696754},
{"learn":[5366874.025],"iteration":414,"passed_time":0.3288711557,"remaining_time":0.06735915237},
{"learn":[5360336.264],"iteration":415,"passed_time":0.3293259112,"remaining_time":0.0664985013},
{"learn":[5355072.835],"iteration":416,"passed_time":0.3297865453,"remaining_time":0.06564096706},
{"learn":[5352088.501],"iteration":417,"passed_time":0.3302512796,"remaining_time":0.06478613619},
{"learn":[5350395.096],"iteration":418,"passed_time":0.3307905321,"remaining_time":0.06394757303},
{"learn":[5346698.271],"iteration":419,"passed_time":0.3316560815,"remaining_time":0.06317258695},
{"learn":[5340394.615],"iteration":420,"passed_time":0.3321285301,"remaining_time":0.06232340589},
{"learn":[5338838.414],"iteration":421,"passed_time":0.332475869,"remaining_time":0.06145288575},
{"learn":[5334996.173],"iteration":422,"passed_time":0.3329439463,"remaining_time":0.06060681766},
{"learn":[5332016.062],"iteration":423,"passed_time":0.3334149684,"remaining_time":0.05976306037},
{"learn":[5330523.545],"iteration":424,"passed_time":0.3338615066,"remaining_time":0.05891673645},
{"learn":[5324722.92],"iteration":425,"passed_time":0.3357067537,"remaining_time":0.05831525769},
{"learn":[5320473.043],"iteration":426,"passed_time":0.33620817,"remaining_time":0.05747821173},
{"learn":[5318001.871],"iteration":427,"passed_time":0.3367174711,"remaining_time":0.05664406056},
{"learn":[5312315.374],"iteration":428,"passed_time":0.3371848936,"remaining_time":0.05580449288},
{"learn":[5310118.702],"iteration":429,"passed_time":0.337636334,"remaining_time":0.05496405437},
{"learn":[5304032.495],"iteration":430,"passed_time":0.3382406556,"remaining_time":0.05414989614},
{"learn":[5302603.004],"iteration":431,"passed_time":0.3387290848,"remaining_time":0.05331846706},
{"learn":[5299812.698],"iteration":432,"passed_time":0.3391515584,"remaining_time":0.05247841666},
{"learn":[5297365.797],"iteration":433,"passed_time":0.3394657723,"remaining_time":0.05162382712},
{"learn":[5290403.302],"iteration":434,"passed_time":0.3399202643,"remaining_time":0.05079268317},
{"learn":[5286854.624],"iteration":435,"passed_time":0.3403860765,"remaining_time":0.04996492866},
{"learn":[5284201.818],"iteration":436,"passed_time":0.3408481752,"remaining_time":0.04913829528},
{"learn":[5280570.564],"iteration":437,"passed_time":0.3414265802,"remaining_time":0.04832978988},
{"learn":[5275689.774],"iteration":438,"passed_time":0.3418685959,"remaining_time":0.0475033812},
{"learn":[5273192.522],"iteration":439,"passed_time":0.3423150535,"remaining_time":0.04667932547},
{"learn":[5267381.858],"iteration":440,"passed_time":0.3427305403,"remaining_time":0.04585283872},
{"learn":[5264027.514],"iteration":441,"passed_time":0.3431499878,"remaining_time":0.04502873143},
{"learn":[5262148.438],"iteration":442,"passed_time":0.3435813598,"remaining_time":0.04420798535},
{"learn":[5260307.503],"iteration":443,"passed_time":0.3440309009,"remaining_time":0.04339128479},
{"learn":[5257421.506],"iteration":444,"passed_time":0.3445295374,"remaining_time":0.04258230238},
{"learn":[5255013.203],"iteration":445,"passed_time":0.3451182652,"remaining_time":0.04178561955},
{"learn":[5253857.712],"iteration":446,"passed_time":0.3454726652,"remaining_time":0.04096208335},
{"learn":[5251467.223],"iteration":447,"passed_time":0.3458236533,"remaining_time":0.04014024547},
{"learn":[5250325.766],"iteration":448,"passed_time":0.3460984303,"remaining_time":0.03931184843},
{"learn":[5247848],"iteration":449,"passed_time":0.3465590512,"remaining_time":0.03850656125},
{"learn":[5242393.624],"iteration":450,"passed_time":0.3470382588,"remaining_time":0.03770482191},
{"learn":[5239103.589],"iteration":451,"passed_time":0.3474972741,"remaining_time":0.03690236539},
{"learn":[5236478.537],"iteration":452,"passed_time":0.3479636504,"remaining_time":0.0361021889},
{"learn":[5230606.559],"iteration":453,"passed_time":0.3485392819,"remaining_time":0.03531455279},
{"learn":[5226865.377],"iteration":454,"passed_time":0.349102487,"remaining_time":0.0345266196},
{"learn":[5224909.116],"iteration":455,"passed_time":0.3496728021,"remaining_time":0.0337403581},
{"learn":[5221703.37],"iteration":456,"passed_time":0.3501862545,"remaining_time":0.03294969134},
{"learn":[5219499.965],"iteration":457,"passed_time":0.3506376019,"remaining_time":0.03215453991},
{"learn":[5217164.707],"iteration":458,"passed_time":0.3510903209,"remaining_time":0.03136100906},
{"learn":[5213292.396],"iteration":459,"passed_time":0.3515386903,"remaining_time":0.03056858176},
{"learn":[5207691.63],"iteration":460,"passed_time":0.3522095228,"remaining_time":0.02979646722},
{"learn":[5205468.868],"iteration":461,"passed_time":0.3538588922,"remaining_time":0.02910527685},
{"learn":[5203257.932],"iteration":462,"passed_time":0.3543827016,"remaining_time":0.02831999991},
{"learn":[5201300.376],"iteration":463,"passed_time":0.3547666132,"remaining_time":0.02752499585},
{"learn":[5199011.366],"iteration":464,"passed_time":0.3552702271,"remaining_time":0.02674076978},
{"learn":[5193085.877],"iteration":465,"passed_time":0.3559684967,"remaining_time":0.0259719504},
{"learn":[5191301.786],"iteration":466,"passed_time":0.356651756,"remaining_time":0.02520237248},
{"learn":[5188642.377],"iteration":467,"passed_time":0.3571180184,"remaining_time":0.02441832604},
{"learn":[5186213.629],"iteration":468,"passed_time":0.3576220934,"remaining_time":0.02363813411},
{"learn":[5184741.627],"iteration":469,"passed_time":0.3580760856,"remaining_time":0.02285592036},
{"learn":[5179639.99],"iteration":470,"passed_time":0.3585325313,"remaining_time":0.02207525139},
{"learn":[5178070.365],"iteration":471,"passed_time":0.3589132765,"remaining_time":0.02129146556},
{"learn":[5174190.599],"iteration":472,"passed_time":0.3594299124,"remaining_time":0.02051714087},
{"learn":[5170619.003],"iteration":473,"passed_time":0.3598462927,"remaining_time":0.01973840424},
{"learn":[5167158.44],"iteration":474,"passed_time":0.3602456556,"remaining_time":0.01896029766},
{"learn":[5163519.449],"iteration":475,"passed_time":0.3606605155,"remaining_time":0.01818456381},
{"learn":[5159760.827],"iteration":476,"passed_time":0.3610652797,"remaining_time":0.01740985625},
{"learn":[5156631.819],"iteration":477,"passed_time":0.3614648247,"remaining_time":0.01663645637},
{"learn":[5152914.87],"iteration":478,"passed_time":0.3618630608,"remaining_time":0.01586456008},
{"learn":[5150803.134],"iteration":479,"passed_time":0.3624650879,"remaining_time":0.015102712},
{"learn":[5148199.766],"iteration":480,"passed_time":0.3629263745,"remaining_time":0.01433596905},
{"learn":[5144554.81],"iteration":481,"passed_time":0.363384766,"remaining_time":0.01357038545},
{"learn":[5140677.246],"iteration":482,"passed_time":0.3638708177,"remaining_time":0.01280704741},
{"learn":[5135544.952],"iteration":483,"passed_time":0.3643177124,"remaining_time":0.01204356074},
{"learn":[5129172.289],"iteration":484,"passed_time":0.3647684243,"remaining_time":0.01128149766},
{"learn":[5126243.109],"iteration":485,"passed_time":0.3652334321,"remaining_time":0.01052112767},
{"learn":[5125292.559],"iteration":486,"passed_time":0.365661255,"remaining_time":0.009760978061},
{"learn":[5123156.582],"iteration":487,"passed_time":0.3662194278,"remaining_time":0.009005395765},
{"learn":[5120626.474],"iteration":488,"passed_time":0.3666961742,"remaining_time":0.008248789195},
{"learn":[5118782.756],"iteration":489,"passed_time":0.3671579738,"remaining_time":0.007493019874},
{"learn":[5115931.617],"iteration":490,"passed_time":0.3676102294,"remaining_time":0.006738273044},
{"learn":[5110760.748],"iteration":491,"passed_time":0.3680602439,"remaining_time":0.005984719413},
{"learn":[5107044.871],"iteration":492,"passed_time":0.368529341,"remaining_time":0.005232668128},
{"learn":[5103736.327],"iteration":493,"passed_time":0.3690533143,"remaining_time":0.004482428918},
{"learn":[5098186.355],"iteration":494,"passed_time":0.3695013977,"remaining_time":0.00373233735},
{"learn":[5096607.088],"iteration":495,"passed_time":0.3699704545,"remaining_time":0.002983632697},
{"learn":[5092631.259],"iteration":496,"passed_time":0.3707210999,"remaining_time":0.002237753118},
{"learn":[5090898.202],"iteration":497,"passed_time":0.3713217929,"remaining_time":0.00149125218},
{"learn":[5087919.846],"iteration":498,"passed_time":0.3717625865,"remaining_time":0.0007450152035},
{"learn":[5085529.361],"iteration":499,"passed_time":0.3721829136,"remaining_time":0}
]}